{"paths":{"0":["E39Laser",0],"1":["E39Jump",0],"2":["bgm_game",0],"3":["E29Attack",0],"4":["E39Step",0],"5":["shurikenfly2",0],"6":["E18_Attack",0],"7":["Kunai",0],"8":["Jumpland",0],"9":["Skillcast207Shuriken",0],"10":["E29Explosion",0],"11":["cursor",0],"12":["slash1",0],"13":["E10Step",0],"14":["StopMove",0],"15":["E27TotemCast",0],"16":["E1_Sword",0],"17":["BlinkStart",0],"18":["getCoin",0],"19":["E39Above2",0],"20":["bgm_main",0],"21":["E40Alert",0],"22":["E2Shoot",0],"23":["SkeletonCharge",0],"24":["select",0],"25":["E15",0],"26":["Dash",0],"27":["E10_attack",0],"28":["E39Attack",0],"29":["Cast203",0],"30":["slash3",0],"31":["rolldash",0],"32":["E39Scratch",0],"33":["highlight_3",0],"34":["E38Attack",0],"35":["SpinAttack",0],"36":["E20Cast",0],"37":["E2_Flee",0],"38":["E27castLightning",0],"39":["jump",0],"40":["E25Die",0],"41":["airslash1",0],"42":["E20FirePillar",0],"43":["E39Above1",0],"44":["E27LightningJolt",0],"45":["E38Fade",0],"46":["E40Born",0],"47":["E24_Shoot",0],"48":["Run",0],"49":["E10_death",0],"50":["drum_1_deeper",0],"51":["E25Attack",0],"52":["BlinkEnd",0],"53":["swoosh2",0],"54":["CreepSpawn",0],"55":["E27LightningTotemFall",0],"56":["ThunderTotemStruck",0],"57":["E27Lightning",0],"58":["thrust1",0],"59":["slash2",0],"60":["E39_death",0],"61":["swoosh1",0],"62":["Spell_Earth_02",0],"63":["E40Exposion",0],"64":["E38AttackEnd",0],"65":["E10Roar",0],"66":["E39AboveLand",0],"67":["E27JoltCast",0],"68":["E27StormBurst",0],"69":["E40Start",0],"70":["E10_Jump",0]},"types":["cc.AudioClip"],"uuids":["00cYHhI9tI3JtMDH2gVQmh","04v0706D1LlrnUAaIsBPc6","0csQlMO7dMMbzjoPctLSmM","0eood/a99D9IqDKrNidToG","0fftsbBONL5puIzsZf1PQk","1dWRcrnfRCQ7cI1gzIBQ1M","1eCunYYvhKq5NMJTwiMww7","27qlPzbglAQ4xTSl0N/Yec","29jWn7vrJBj5L1gfwpZNUM","2aAnTmum9LhaWaNjddZZ/4","2dGqHml2ZKB6wwgum5/Cvz","2dPpZuOENG7IMnngPQAcn3","33RtQnv0dDL6H6EJB+AMHA","33Yg8pj1hCAJQTW0cPwuhW","37KUyYtJhMNLAngsij15bu","38BA9uTclFV53k4lGQI1Mx","38h77DaPVIvaEJTg/sY4iB","39ADa4OsBObIWt5u5paIU6","3eOMXB2QFNzL4gjOCeHNAg","47gXuJm3ZCX4aeNAQxnDW6","4aU97yVNVPHb9fKBGcBGDs","4dO9tRxwRN5J60U2xGZ2US","53OIYjD9FHeaYy1GZs9hqM","568nMbe3RC1pA+b1IZZEbY","5bUWyaq6dKsp3AvOEAK/Wl","5eFlMse11FRLcktziqd5F7","65096u6pxM2LzfzJrU6V5z","69zQEeFwNFQ6rHYN4DXMqy","6cIF/KTUZNxZQRl/wKFx6d","6fCuli6wNBcJ+1QlPpzPnQ","74sC5IpU5BCYZ2Vjl26kih","7dINcrQ6hNyLpfhoOATq7/","7eCt0DBXdF9YtudO6LPlsj","87HyEG4CpPEZ2YgG0HMWhs","88+G0qj9BCjquH7vq4d2aF","8ehCyAOi9Oh5A5UGOqWOiB","8fWTf0pHFINKGyoXrsajJW","94ObIPfXhDLKDw1d/n4EbV","9a8p9NxapKl7205ynl9PBU","9dQn+B7wtGoJmyOoiwZQbI","a1BkjU2MxJ3KeSh6zvSc4k","b21Y3k9fVBMI00Pp+q+lBZ","b3iC4StVpOdIC2/vN6qUbo","bbQWjIk4FLxoLpeuhQ+pn5","c1+sXtaNxPv6nzgCK7VqxJ","c24d2dzIhN/4IUN5ag7OUJ","c4oRAVaABPjo54CtB+HY9+","c49JYJpxFGVoBk13jJqpo8","c6HsNqZbxNOLnHxDaACEwI","c6sL0uNUhOT6IZWbeqMqoJ","c890HiI+hAW4cHINXBjEqw","ca5ij4zSdERbgzkFSZHJuI","cbNjk3sPJIxozSX3TT1YtT","cchC1O10RDGbZdnlNyqVbb","cdLM90O+ZJ9pTI4lYXLCo3","d3516eaWRFI7VoVvqz2JAa","d4VQccG41AcJMVO/JZTAKK","d7PyCT13NIebwnGPsxn9uf","d76/JbOb1EYrP0dBSDuX+C","d9KIW96JZNOL8ooYLR5DJc","e0/so5fCNFuYjA1NrMNQ/U","e1f5vZmf9Cybx832Rz0Dsd","e30sn5/5VP2L1PGNgrJkco","e8nAl2zm5NL6TbvoHk91oJ","f54lwVwmFG1ogT+iB59sLv","f57f3QAiBGL7W4CO144HBq","f7gTDvhnRKx4OYEnuuChqn","fbMeumPmlOpo1G/AN/nTiT","fdeSZyTwdItK2kOddYE9/t","fePUMCirZOIYhPoZBue3Uv","ffbPuiBNFKh62BHF9ydazq"],"scenes":{},"redirect":[],"deps":[],"packs":{},"name":"sounds","importBase":"import","nativeBase":"native","debug":false,"isZip":false,"encrypted":false,"versions":{"import":[0,"5ddc1",1,"033cf",2,"8a031",3,"18327",4,"9761e",5,"6bd3f",6,"05646",7,"21465",8,"67106",9,"3601b",10,"09fff",11,"bae08",12,"3a259",13,"f85a1",14,"ef210",15,"5cc74",16,"e61cc",17,"b756c",18,"68afe",19,"ba2e7",20,"f09a2",21,"ad079",22,"6a477",23,"5e433",24,"63710",25,"4ef06",26,"30f1f",27,"79535",28,"e2610",29,"95720",30,"87333",31,"7b96c",32,"4435d",33,"b222b",34,"55e94",35,"2eaef",36,"c4393",37,"d48fc",38,"6c92a",39,"f3b02",40,"7ada1",41,"dc9e4",42,"f720c",43,"e6d00",44,"6a6af",45,"89050",46,"b59ba",47,"839e6",48,"ec8a0",49,"9223a",50,"e2a78",51,"4a022",52,"7ad1d",53,"cf983",54,"54ca1",55,"5e5c0",56,"ba470",57,"74b98",58,"3b05d",59,"4505c",60,"31dcc",61,"e2fe9",62,"7fe04",63,"f22b2",64,"31578",65,"e104a",66,"8fc12",67,"928b5",68,"2cbb4",69,"b8bc0",70,"fc1b9"],"native":[0,"65308",1,"72d59",2,"421d3",3,"bdc54",4,"23112",5,"8afc9",6,"ddb5a",7,"ee891",8,"1669d",9,"36bbf",10,"6ca40",11,"803c7",12,"32931",13,"fc1e1",14,"8cc84",15,"f3c0b",16,"053ca",17,"f47f1",18,"109f4",19,"54039",20,"130c5",21,"2472b",22,"2de2d",23,"47ab3",24,"d0999",25,"b1067",26,"53daa",27,"fe4e5",28,"6650e",29,"0fe5d",30,"cb75e",31,"ae4f7",32,"2d69d",33,"bc5e5",34,"98f21",35,"aeac9",36,"3dcea",37,"e522b",38,"f61a1",39,"f839b",40,"7f505",41,"20bc1",42,"f08c3",43,"e9fd5",44,"598d1",45,"8e0e7",46,"67fbe",47,"0f0a9",48,"c366e",49,"0402f",50,"5e001",51,"7d040",52,"e0af8",53,"723ad",54,"676c1",55,"53f78",56,"7be37",57,"2ded3",58,"4a6c1",59,"e92b2",60,"53161",61,"10851",62,"99a52",63,"91365",64,"5d1d6",65,"fd27d",66,"4d417",67,"b0690",68,"c5e71",69,"6f118",70,"47d37"]}}